app.py
j2s3_cli-1.1.2.dist-info/METADATA
j2s3_cli-1.1.2.dist-info/RECORD
j2s3_cli-1.1.2.dist-info/WHEEL
j2s3_cli-1.1.2.dist-info/entry_points.txt
j2s3_cli-1.1.2.dist-info/top_level.txt
src/__init__.py
src/app.py
