Metadata-Version: 2.1
Name: j2s3-cli
Version: 1.1.2
Summary: A cli for publishing Java maven projects to an S3 maven repository
Home-page: https://github.com/jackmahoney/j2s3-cli
Author: jackmahoney
Author-email: jackmahoney212@gmail.com
License: Apache 2.0
Platform: UNKNOWN
Requires-Python: >=3
Requires-Dist: j2s3 (==1.0.2)
Requires-Dist: click (==6.7)
